ytscribe/__init__.py
ytscribe/transcribe.py
ytscribe-0.0.4.dist-info/METADATA
ytscribe-0.0.4.dist-info/WHEEL
ytscribe-0.0.4.dist-info/top_level.txt
ytscribe-0.0.4.dist-info/RECORD
