Metadata-Version: 2.1
Name: ytscribe
Version: 0.0.4
Summary: Transcribe YouTube videos
Author: Vamsi Uppala
Author-email: uvvamsikrishna@gmail.com
Keywords: python,first package
Classifier: Development Status :: 3 - Alpha
Classifier: Intended Audience :: Education
Classifier: Programming Language :: Python :: 2
Classifier: Programming Language :: Python :: 3
Classifier: Operating System :: MacOS :: MacOS X
Classifier: Operating System :: Microsoft :: Windows
